task3/counter.sv
//==============================================================
// Lab 1 - Task 3 : Vbuddy parameter & flag (one-shot mode)
//==============================================================
// Step 1: Loadable counter
// Pressing the Vbuddy switch loads the counter with Vbuddy's parameter value.
//==============================================================

module counter #(
  parameter WIDTH = 8
)(
  input  logic             clk,      // clock
  input  logic             rst,      // reset
  input  logic             sw,   // load trigger from Vbuddy flag
  input  logic [WIDTH-1:0] v,        // value to preload from Vbuddy
  output logic [WIDTH-1:0] count     // count output
);

  // STEP 1: Loadable counter (ACTIVE)
  always_ff @(posedge clk) begin
    if (rst)
      count <= {WIDTH{1'b0}};        // reset to zero
    else if (sw)
      count <= v;                    // load Vbuddy parameter value
    else
      count <= count + 1'b1;         // normal counting
  end

  //==============================================================
  // STEP 2: Single-step counter (COMMENTED OUT)
  //--------------------------------------------------------------
  // Uncomment this block and comment out the above one
  // to make the counter increment **only** when the Vbuddy switch is pressed.
  //--------------------------------------------------------------
  /*
  always_ff @(posedge clk) begin
    if (rst)
      count <= {WIDTH{1'b0}};
    else if (sw)
      count <= count + 1'b1;         // increment only when pressed
  end
  */
  //==============================================================

endmodule

task3/counter.vcd
$version Generated by VerilatedVcd $end
$date Thu Oct 23 23:36:53 2025 $end
$timescale 1ps $end

 $scope module TOP $end
  $var wire  1 # clk $end
  $var wire  8 ' count [7:0] $end
  $var wire  1 $ rst $end
  $var wire  1 % sw $end
  $var wire  8 & v [7:0] $end
  $scope module counter $end
   $var wire 32 ( WIDTH [31:0] $end
   $var wire  1 # clk $end
   $var wire  8 ' count [7:0] $end
   $var wire  1 $ rst $end
   $var wire  1 % sw $end
   $var wire  8 & v [7:0] $end
  $upscope $end
 $upscope $end
$enddefinitions $end


#0
0#
1$
0%
b00000000 &
b00000000 '
b00000000000000000000000000001000 (
#1
1#
#2
0#
1%
#3
1#
#4
0#
0%
#5
1#
#6
0#
0$
#7
1#
b00000001 '
#8
0#
#9
1#
b00000010 '
#10
0#
#11
1#
b00000011 '
#12
0#
#13
1#
b00000100 '
#14
0#
#15
1#
b00000101 '
#16
0#
#17
1#
b00000110 '
#18
0#
#19
1#
b00000111 '
#20
0#
#21
1#
b00001000 '
#22
0#
#23
1#
b00001001 '
#24
0#
#25
1#
b00001010 '
#26
0#
#27
1#
b00001011 '
#28
0#
#29
1#
b00001100 '
#30
0#
#31
1#
b00001101 '
#32
0#
#33
1#
b00001110 '
#34
0#
#35
1#
b00001111 '
#36
0#
#37
1#
b00010000 '
#38
0#
#39
1#
b00010001 '
#40
0#
#41
1#
b00010010 '
#42
0#
#43
1#
b00010011 '
#44
0#
#45
1#
b00010100 '
#46
0#
#47
1#
b00010101 '
#48
0#
#49
1#
b00010110 '
#50
0#
#51
1#
b00010111 '
#52
0#
#53
1#
b00011000 '
#54
0#
#55
1#
b00011001 '
#56
0#
#57
1#
b00011010 '
#58
0#
#59
1#
b00011011 '
#60
0#
#61
1#
b00011100 '
#62
0#
#63
1#
b00011101 '
#64
0#
#65
1#
b00011110 '
#66
0#
#67
1#
b00011111 '
#68
0#
#69
1#
b00100000 '
#70
0#
#71
1#
b00100001 '
#72
0#
#73
1#
b00100010 '
#74
0#
#75
1#
b00100011 '
#76
0#
#77
1#
b00100100 '
#78
0#
#79
1#
b00100101 '
#80
0#
#81
1#
b00100110 '
#82
0#
#83
1#
b00100111 '
#84
0#
#85
1#
b00101000 '
#86
0#
#87
1#
b00101001 '
#88
0#
#89
1#
b00101010 '
#90
0#
#91
1#
b00101011 '
#92
0#
#93
1#
b00101100 '
#94
0#
#95
1#
b00101101 '
#96
0#
#97
1#
b00101110 '
#98
0#
#99
1#
b00101111 '
#100
0#
#101
1#
b00110000 '
#102
0#
#103
1#
b00110001 '
#104
0#
#105
1#
b00110010 '
#106
0#
#107
1#
b00110011 '
#108
0#
#109
1#
b00110100 '
#110
0#
#111
1#
b00110101 '
#112
0#
#113
1#
b00110110 '
#114
0#
#115
1#
b00110111 '
#116
0#
#117
1#
b00111000 '
#118
0#
#119
1#
b00111001 '
#120
0#
#121
1#
b00111010 '
#122
0#
#123
1#
b00111011 '
#124
0#
#125
1#
b00111100 '
#126
0#
#127
1#
b00111101 '
#128
0#
#129
1#
b00111110 '
#130
0#
#131
1#
b00111111 '
#132
0#
#133
1#
b01000000 '
#134
0#
#135
1#
b01000001 '
#136
0#
#137
1#
b01000010 '
#138
0#
#139
1#
b01000011 '
#140
0#
#141
1#
b01000100 '
#142
0#
#143
1#
b01000101 '
#144
0#
#145
1#
b01000110 '
#146
0#
#147
1#
b01000111 '
#148
0#
#149
1#
b01001000 '
#150
0#
#151
1#
b01001001 '
#152
0#
#153
1#
b01001010 '
#154
0#
#155
1#
b01001011 '
#156
0#
#157
1#
b01001100 '
#158
0#
#159
1#
b01001101 '
#160
0#
#161
1#
b01001110 '
#162
0#
#163
1#
b01001111 '
#164
0#
#165
1#
b01010000 '
#166
0#
#167
1#
b01010001 '
#168
0#
#169
1#
b01010010 '
#170
0#
#171
1#
b01010011 '
#172
0#
#173
1#
b01010100 '
#174
0#
#175
1#
b01010101 '
#176
0#
#177
1#
b01010110 '
#178
0#
#179
1#
b01010111 '
#180
0#
#181
1#
b01011000 '
#182
0#
#183
1#
b01011001 '
#184
0#
#185
1#
b01011010 '
#186
0#
#187
1#
b01011011 '
#188
0#
#189
1#
b01011100 '
#190
0#
1%
#191
1#
b00000000 '
#192
0#
0%
#193
1#
b00000001 '
#194
0#
#195
1#
b00000010 '
#196
0#
#197
1#
b00000011 '
#198
0#
#199
1#
b00000100 '
#200
0#
#201
1#
b00000101 '
#202
0#
#203
1#
b00000110 '
#204
0#
#205
1#
b00000111 '
#206
0#
#207
1#
b00001000 '
#208
0#
#209
1#
b00001001 '
#210
0#
#211
1#
b00001010 '
#212
0#
#213
1#
b00001011 '
#214
0#
#215
1#
b00001100 '
#216
0#
#217
1#
b00001101 '
#218
0#
#219
1#
b00001110 '
#220
0#
#221
1#
b00001111 '
#222
0#
#223
1#
b00010000 '
#224
0#
#225
1#
b00010001 '
#226
0#
#227
1#
b00010010 '
#228
0#
#229
1#
b00010011 '
#230
0#
#231
1#
b00010100 '
#232
0#
#233
1#
b00010101 '
#234
0#
#235
1#
b00010110 '
#236
0#
#237
1#
b00010111 '
#238
0#
#239
1#
b00011000 '
#240
0#
#241
1#
b00011001 '
#242
0#
#243
1#
b00011010 '
#244
0#
#245
1#
b00011011 '
#246
0#
#247
1#
b00011100 '
#248
0#
#249
1#
b00011101 '
#250
0#
#251
1#
b00011110 '
#252
0#
#253
1#
b00011111 '
#254
0#
#255
1#
b00100000 '
#256
0#
#257
1#
b00100001 '
#258
0#
#259
1#
b00100010 '
#260
0#
#261
1#
b00100011 '
#262
0#
#263
1#
b00100100 '
#264
0#
#265
1#
b00100101 '
#266
0#
#267
1#
b00100110 '
#268
0#
#269
1#
b00100111 '
#270
0#
#271
1#
b00101000 '
#272
0#
#273
1#
b00101001 '
#274
0#
1%
#275
1#
b00000000 '
#276
0#
0%
#277
1#
b00000001 '
#278
0#
#279
1#
b00000010 '
#280
0#
#281
1#
b00000011 '
#282
0#
#283
1#
b00000100 '
#284
0#
#285
1#
b00000101 '
#286
0#
#287
1#
b00000110 '
#288
0#
#289
1#
b00000111 '
#290
0#
#291
1#
b00001000 '
#292
0#
#293
1#
b00001001 '
#294
0#
#295
1#
b00001010 '
#296
0#
#297
1#
b00001011 '
#298
0#
#299
1#
b00001100 '
#300
0#
#301
1#
b00001101 '
#302
0#
#303
1#
b00001110 '
#304
0#
#305
1#
b00001111 '
#306
0#
#307
1#
b00010000 '
#308
0#
#309
1#
b00010001 '
#310
0#
#311
1#
b00010010 '
#312
0#
#313
1#
b00010011 '
#314
0#
#315
1#
b00010100 '
#316
0#
#317
1#
b00010101 '
#318
0#
#319
1#
b00010110 '
#320
0#
#321
1#
b00010111 '
#322
0#
#323
1#
b00011000 '
#324
0#
#325
1#
b00011001 '
#326
0#
#327
1#
b00011010 '
#328
0#
#329
1#
b00011011 '
#330
0#
#331
1#
b00011100 '
#332
0#
#333
1#
b00011101 '
#334
0#
#335
1#
b00011110 '
#336
0#
#337
1#
b00011111 '
#338
0#
#339
1#
b00100000 '
#340
0#
#341
1#
b00100001 '
#342
0#
#343
1#
b00100010 '
#344
0#
#345
1#
b00100011 '
#346
0#
#347
1#
b00100100 '
#348
0#
#349
1#
b00100101 '
#350
0#
#351
1#
b00100110 '
#352
0#
1%
#353
1#
b00000000 '
#354
0#
0%
#355
1#
b00000001 '
#356
0#
#357
1#
b00000010 '
#358
0#
#359
1#
b00000011 '
#360
0#
#361
1#
b00000100 '
#362
0#
#363
1#
b00000101 '
#364
0#
#365
1#
b00000110 '
#366
0#
#367
1#
b00000111 '
#368
0#
#369
1#
b00001000 '
#370
0#
#371
1#
b00001001 '
#372
0#
#373
1#
b00001010 '
#374
0#
#375
1#
b00001011 '
#376
0#
#377
1#
b00001100 '
#378
0#
#379
1#
b00001101 '
#380
0#
#381
1#
b00001110 '
#382
0#
#383
1#
b00001111 '
#384
0#
#385
1#
b00010000 '
#386
0#
#387
1#
b00010001 '
#388
0#
#389
1#
b00010010 '
#390
0#
#391
1#
b00010011 '
#392
0#
#393
1#
b00010100 '
#394
0#
#395
1#
b00010101 '
#396
0#
#397
1#
b00010110 '
#398
0#
#399
1#
b00010111 '
#400
0#
#401
1#
b00011000 '
#402
0#
#403
1#
b00011001 '
#404
0#
#405
1#
b00011010 '
#406
0#
#407
1#
b00011011 '
#408
0#
#409
1#
b00011100 '
#410
0#
#411
1#
b00011101 '
#412
0#
#413
1#
b00011110 '
#414
0#
#415
1#
b00011111 '
#416
0#
#417
1#
b00100000 '
#418
0#
#419
1#
b00100001 '
#420
0#
#421
1#
b00100010 '
#422
0#
#423
1#
b00100011 '
#424
0#
#425
1#
b00100100 '
#426
0#
#427
1#
b00100101 '
#428
0#
#429
1#
b00100110 '
#430
0#
#431
1#
b00100111 '
#432
0#
#433
1#
b00101000 '
#434
0#
#435
1#
b00101001 '
#436
0#
#437
1#
b00101010 '
#438
0#
#439
1#
b00101011 '
#440
0#
#441
1#
b00101100 '
#442
0#
1%
#443
1#
b00000000 '
#444
0#
0%
#445
1#
b00000001 '
#446
0#
#447
1#
b00000010 '
#448
0#
#449
1#
b00000011 '
#450
0#
#451
1#
b00000100 '
#452
0#
#453
1#
b00000101 '
#454
0#
#455
1#
b00000110 '
#456
0#
#457
1#
b00000111 '
#458
0#
#459
1#
b00001000 '
#460
0#
#461
1#
b00001001 '
#462
0#
#463
1#
b00001010 '
#464
0#
#465
1#
b00001011 '
#466
0#
#467
1#
b00001100 '
#468
0#
#469
1#
b00001101 '
#470
0#
#471
1#
b00001110 '
#472
0#
#473
1#
b00001111 '
#474
0#
#475
1#
b00010000 '
#476
0#
#477
1#
b00010001 '
#478
0#
#479
1#
b00010010 '
#480
0#
1%
#481
1#
b00000000 '
#482
0#
0%
#483
1#
b00000001 '
#484
0#
#485
1#
b00000010 '
#486
0#
#487
1#
b00000011 '
#488
0#
#489
1#
b00000100 '
#490
0#
#491
1#
b00000101 '
#492
0#
1%
#493
1#
b00000000 '
#494
0#
0%
#495
1#
b00000001 '
#496
0#
#497
1#
b00000010 '
#498
0#
#499
1#
b00000011 '
#500
0#
#501
1#
b00000100 '
#502
0#
#503
1#
b00000101 '
#504
0#
1%
#505
1#
b00000000 '
#506
0#
0%
#507
1#
b00000001 '
#508
0#
#509
1#
b00000010 '
#510
0#
#511
1#
b00000011 '
#512
0#
#513
1#
b00000100 '
#514
0#
#515
1#
b00000101 '
#516
0#
#517
1#
b00000110 '
#518
0#
1%
#519
1#
b00000000 '
#520
0#
0%
#521
1#
b00000001 '
#522
0#
#523
1#
b00000010 '
#524
0#
#525
1#
b00000011 '
#526
0#
#527
1#
b00000100 '
#528
0#
#529
1#
b00000101 '
#530
0#
#531
1#
b00000110 '
#532
0#
#533
1#
b00000111 '
#534
0#
#535
1#
b00001000 '
#536
0#
#537
1#
b00001001 '
#538
0#
#539
1#
b00001010 '
#540
0#
#541
1#
b00001011 '
#542
0#
#543
1#
b00001100 '
#544
0#
1%
#545
1#
b00000000 '
#546
0#
0%
#547
1#
b00000001 '
#548
0#
#549
1#
b00000010 '
#550
0#
#551
1#
b00000011 '
#552
0#
#553
1#
b00000100 '
#554
0#
#555
1#
b00000101 '
#556
0#
#557
1#
b00000110 '
#558
0#
#559
1#
b00000111 '
#560
0#
#561
1#
b00001000 '
#562
0#
1%
#563
1#
b00000000 '
#564
0#
0%
#565
1#
b00000001 '
#566
0#
#567
1#
b00000010 '
#568
0#
#569
1#
b00000011 '
#570
0#
#571
1#
b00000100 '
#572
0#
#573
1#
b00000101 '
#574
0#
#575
1#
b00000110 '
#576
0#
#577
1#
b00000111 '
#578
0#
1%
#579
1#
b00000000 '
#580
0#
0%
#581
1#
b00000001 '
#582
0#
#583
1#
b00000010 '
#584
0#
#585
1#
b00000011 '
#586
0#
#587
1#
b00000100 '
#588
0#
#589
1#
b00000101 '
#590
0#
#591
1#
b00000110 '
#592
0#
#593
1#
b00000111 '
#594
0#
1%
#595
1#
b00000000 '
#596
0#
0%
#597
1#
b00000001 '
#598
0#
#599
1#
b00000010 '
#600
0#
#601
1#
b00000011 '
#602
0#
#603
1#
b00000100 '
#604
0#
#605
1#
b00000101 '
#606
0#
#607
1#
b00000110 '
#608
0#
#609
1#
b00000111 '
#610
0#
#611
1#
b00001000 '
#612
0#
#613
1#
b00001001 '
#614
0#
#615
1#
b00001010 '
#616
0#
#617
1#
b00001011 '
#618
0#
#619
1#
b00001100 '
#620
0#
#621
1#
b00001101 '
#622
0#
#623
1#
b00001110 '
#624
0#
#625
1#
b00001111 '
#626
0#
#627
1#
b00010000 '
#628
0#
#629
1#
b00010001 '
#630
0#
#631
1#
b00010010 '
#632
0#
#633
1#
b00010011 '
#634
0#
#635
1#
b00010100 '
#636
0#
#637
1#
b00010101 '
#638
0#
1%
#639
1#
b00000000 '
#640
0#
0%
#641
1#
b00000001 '
#642
0#
#643
1#
b00000010 '
#644
0#
#645
1#
b00000011 '
#646
0#
#647
1#
b00000100 '
#648
0#
1%
#649
1#
b00000000 '
#650
0#
0%
#651
1#
b00000001 '
#652
0#
#653
1#
b00000010 '
#654
0#
#655
1#
b00000011 '
#656
0#
#657
1#
b00000100 '
#658
0#
#659
1#
b00000101 '
#660
0#
#661
1#
b00000110 '
#662
0#
1%
#663
1#
b00000000 '
#664
0#
0%
#665
1#
b00000001 '
#666
0#
#667
1#
b00000010 '
#668
0#
#669
1#
b00000011 '
#670
0#
1%
#671
1#
b00000000 '
#672
0#
0%
#673
1#
b00000001 '
#674
0#
#675
1#
b00000010 '
#676
0#
#677
1#
b00000011 '
#678
0#
#679
1#
b00000100 '
#680
0#
#681
1#
b00000101 '
#682
0#
#683
1#
b00000110 '
#684
0#
1%
#685
1#
b00000000 '
#686
0#
0%
#687
1#
b00000001 '
#688
0#
#689
1#
b00000010 '
#690
0#
#691
1#
b00000011 '
#692
0#
#693
1#
b00000100 '
#694
0#
#695
1#
b00000101 '
#696
0#
#697
1#
b00000110 '
#698
0#
1%
#699
1#
b00000000 '
#700
0#
0%
#701
1#
b00000001 '
#702
0#
#703
1#
b00000010 '
#704
0#
#705
1#
b00000011 '
#706
0#
#707
1#
b00000100 '
#708
0#
#709
1#
b00000101 '
#710
0#
#711
1#
b00000110 '
#712
0#
1%
#713
1#
b00000000 '
#714
0#
0%
#715
1#
b00000001 '
#716
0#
#717
1#
b00000010 '
#718
0#
#719
1#
b00000011 '
#720
0#
#721
1#
b00000100 '
#722
0#
#723
1#
b00000101 '
#724
0#
#725
1#
b00000110 '
#726
0#
#727
1#
b00000111 '
#728
0#
1%
#729
1#
b00000000 '
#730
0#
0%
#731
1#
b00000001 '
#732
0#
#733
1#
b00000010 '
#734
0#
#735
1#
b00000011 '
#736
0#
#737
1#
b00000100 '
#738
0#
#739
1#
b00000101 '
#740
0#
#741
1#
b00000110 '
#742
0#
1%
#743
1#
b00000000 '
#744
0#
0%
#745
1#
b00000001 '
#746
0#
#747
1#
b00000010 '
#748
0#
#749
1#
b00000011 '
#750
0#
#751
1#
b00000100 '
#752
0#
#753
1#
b00000101 '
#754
0#
#755
1#
b00000110 '
#756
0#
1%
#757
1#
b00000000 '
#758
0#
0%
#759
1#
b00000001 '
#760
0#
#761
1#
b00000010 '
#762
0#
#763
1#
b00000011 '
#764
0#
#765
1#
b00000100 '
#766
0#
#767
1#
b00000101 '
#768
0#
#769
1#
b00000110 '
#770
0#
#771
1#
b00000111 '
#772
0#
#773
1#
b00001000 '
#774
0#
#775
1#
b00001001 '
#776
0#
#777
1#
b00001010 '
#778
0#
#779
1#
b00001011 '
#780
0#
#781
1#
b00001100 '
#782
0#
#783
1#
b00001101 '
#784
0#
#785
1#
b00001110 '
#786
0#
#787
1#
b00001111 '
#788
0#
#789
1#
b00010000 '
#790
0#
#791
1#
b00010001 '
#792
0#
#793
1#
b00010010 '
#794
0#
#795
1#
b00010011 '
#796
0#
#797
1#
b00010100 '
#798
0#
#799
1#
b00010101 '
#800
0#
#801
1#
b00010110 '
#802
0#
#803
1#
b00010111 '
#804
0#
#805
1#
b00011000 '
#806
0#
#807
1#
b00011001 '
#808
0#
#809
1#
b00011010 '
#810
0#
#811
1#
b00011011 '
#812
0#
#813
1#
b00011100 '
#814
0#
#815
1#
b00011101 '
#816
0#
#817
1#
b00011110 '
#818
0#
#819
1#
b00011111 '
#820
0#
#821
1#
b00100000 '
#822
0#
#823
1#
b00100001 '
#824
0#
#825
1#
b00100010 '
#826
0#
#827
1#
b00100011 '
#828
0#
#829
1#
b00100100 '
#830
0#
#831
1#
b00100101 '
#832
0#
#833
1#
b00100110 '
#834
0#
#835
1#
b00100111 '
#836
0#
#837
1#
b00101000 '
#838
0#
#839
1#
b00101001 '
#840
0#
#841
1#
b00101010 '
#842
0#
#843
1#
b00101011 '
#844
0#
#845
1#
b00101100 '
#846
0#
#847
1#
b00101101 '
#848
0#
#849
1#
b00101110 '
#850
0#
1%
#851
1#
b00000000 '
#852
0#
0%
#853
1#
b00000001 '
#854
0#
#855
1#
b00000010 '
#856
0#
#857
1#
b00000011 '
#858
0#
#859
1#
b00000100 '
#860
0#
#861
1#
b00000101 '
#862
0#
#863
1#
b00000110 '
#864
0#
#865
1#
b00000111 '
#866
0#
#867
1#
b00001000 '
#868
0#
#869
1#
b00001001 '
#870
0#
#871
1#
b00001010 '
#872
0#
#873
1#
b00001011 '
#874
0#
#875
1#
b00001100 '
#876
0#
#877
1#
b00001101 '
#878
0#
#879
1#
b00001110 '
#880
0#
#881
1#
b00001111 '
#882
0#
#883
1#
b00010000 '
#884
0#
#885
1#
b00010001 '
#886
0#
#887
1#
b00010010 '
#888
0#
#889
1#
b00010011 '
#890
0#
#891
1#
b00010100 '
#892
0#
#893
1#
b00010101 '
#894
0#
#895
1#
b00010110 '
#896
0#
1%
#897
1#
b00000000 '
#898
0#
0%
#899
1#
b00000001 '
#900
0#
#901
1#
b00000010 '
#902
0#
#903
1#
b00000011 '
#904
0#
#905
1#
b00000100 '
#906
0#
#907
1#
b00000101 '
#908
0#
#909
1#
b00000110 '
#910
0#
#911
1#
b00000111 '
#912
0#
#913
1#
b00001000 '
#914
0#
#915
1#
b00001001 '
#916
0#
#917
1#
b00001010 '
#918
0#
#919
1#
b00001011 '
#920
0#
#921
1#
b00001100 '
#922
0#
#923
1#
b00001101 '
#924
0#
#925
1#
b00001110 '
#926
0#
#927
1#
b00001111 '
#928
0#
#929
1#
b00010000 '
#930
0#
#931
1#
b00010001 '
#932
0#
#933
1#
b00010010 '
#934
0#
#935
1#
b00010011 '
#936
0#
#937
1#
b00010100 '
#938
0#
#939
1#
b00010101 '
#940
0#
#941
1#
b00010110 '
#942
0#
#943
1#
b00010111 '
#944
0#
#945
1#
b00011000 '
#946
0#
#947
1#
b00011001 '
#948
0#
#949
1#
b00011010 '
#950
0#
#951
1#
b00011011 '
#952
0#
#953
1#
b00011100 '
#954
0#
#955
1#
b00011101 '
#956
0#
1%
#957
1#
b00000000 '
#958
0#
0%
#959
1#
b00000001 '
#960
0#
#961
1#
b00000010 '
#962
0#
#963
1#
b00000011 '
#964
0#
#965
1#
b00000100 '
#966
0#
#967
1#
b00000101 '
#968
0#
#969
1#
b00000110 '
#970
0#
#971
1#
b00000111 '
#972
0#
1%
#973
1#
b00000000 '
#974
0#
0%
#975
1#
b00000001 '
#976
0#
#977
1#
b00000010 '
#978
0#
#979
1#
b00000011 '
#980
0#
#981
1#
b00000100 '
#982
0#
#983
1#
b00000101 '
#984
0#
#985
1#
b00000110 '
#986
0#
#987
1#
b00000111 '
#988
0#
#989
1#
b00001000 '
#990
0#
#991
1#
b00001001 '
#992
0#
#993
1#
b00001010 '
#994
0#
#995
1#
b00001011 '
#996
0#
#997
1#
b00001100 '
#998
0#
#999
1#
b00001101 '
