task1/counter_async.sv
module counter_async #(
    parameter WIDTH = 8             // Counter bit width
)(
    input  logic clk,               // Clock
    input  logic rst,               // Asynchronous reset (active high)
    input  logic en,                // Enable counting
    output logic [WIDTH-1:0] count  // Counter output
);

    // Asynchronous reset: triggers on posedge clk or posedge rst
    always_ff @(posedge clk or posedge rst) begin
        if (rst)
            count <= {WIDTH{1'b0}};                 // Immediate reset to 0
        else
            count <= count + {{WIDTH-1{1'b0}}, en}; // Increment by 1 if en=1
    end

endmodule

task1/Vcounter_async.vcd
$version Generated by VerilatedVcd $end
$date Thu Oct 23 22:12:34 2025 $end
$timescale 1ps $end

 $scope module TOP $end
  $var wire  1 # clk $end
  $var wire  8 & count [7:0] $end
  $var wire  1 % en $end
  $var wire  1 $ rst $end
  $scope module counter_async $end
   $var wire 32 ' WIDTH [31:0] $end
   $var wire  1 # clk $end
   $var wire  8 & count [7:0] $end
   $var wire  1 % en $end
   $var wire  1 $ rst $end
  $upscope $end
 $upscope $end
$enddefinitions $end


#0
1#
1$
0%
b00000000 &
b00000000000000000000000000001000 '
#10
0#
#20
1#
#30
0#
#40
1#
0$
#50
0#
1%
#60
1#
b00000001 &
#70
0#
#80
1#
b00000010 &
#90
0#
#100
1#
b00000011 &
#110
0#
#120
1#
b00000100 &
#130
0#
#140
1#
b00000101 &
#150
0#
#160
1#
b00000110 &
#170
0#
#180
1#
b00000111 &
#190
0#
#200
1#
b00001000 &
#210
0#
#220
1#
b00001001 &
#230
0#
#240
1#
b00001010 &
#250
0#
#260
1#
b00001011 &
#270
0#
#280
1#
b00001100 &
#290
0#
#300
1#
b00001101 &
#310
0#
#320
1#
b00001110 &
#330
0#
#340
1#
b00001111 &
#350
0#
#360
1#
b00010000 &
#370
0#
#380
1#
b00010001 &
#390
0#
#400
1#
b00010010 &
#410
0#
#420
1#
b00010011 &
#430
0#
#440
1#
b00010100 &
#450
0#
#460
1#
b00010101 &
#470
0#
#480
1#
b00010110 &
#490
0#
#500
1#
1$
b00000000 &
#510
0#
#520
1#
#530
0#
#540
1#
#550
0#
0$
#560
1#
b00000001 &
#570
0#
#580
1#
b00000010 &
#590
0#
#600
1#
b00000011 &
#610
0#
#620
1#
b00000100 &
#630
0#
#640
1#
b00000101 &
#650
0#
#660
1#
b00000110 &
#670
0#
#680
1#
b00000111 &
#690
0#
#700
1#
b00001000 &
#710
0#
#720
1#
b00001001 &
#730
0#
#740
1#
b00001010 &
#750
0#
#760
1#
b00001011 &
#770
0#
#780
1#
b00001100 &
#790
0#
#800
1#
b00001101 &
#810
0#
#820
1#
b00001110 &
#830
0#
#840
1#
b00001111 &
#850
0#
#860
1#
b00010000 &
#870
0#
#880
1#
b00010001 &
#890
0#
#900
1#
b00010010 &
#910
0#
#920
1#
b00010011 &
#930
0#
#940
1#
b00010100 &
#950
0#
#960
1#
b00010101 &
#970
0#
#980
1#
b00010110 &
#990
0#
#1000
1#
b00010111 &
#1010
0#
#1020
1#
b00011000 &
#1030
0#
#1040
1#
b00011001 &
#1050
0#
#1060
1#
b00011010 &
#1070
0#
#1080
1#
b00011011 &
#1090
0#
#1100
1#
b00011100 &
#1110
0#
#1120
1#
b00011101 &
#1130
0#
#1140
1#
b00011110 &
#1150
0#
#1160
1#
b00011111 &
#1170
0#
#1180
1#
b00100000 &
#1190
0#
#1200
1#
b00100001 &
#1210
0#
#1220
1#
b00100010 &
#1230
0#
#1240
1#
b00100011 &
#1250
0#
#1260
1#
b00100100 &
#1270
0#
#1280
1#
b00100101 &
#1290
0#
#1300
1#
b00100110 &
#1310
0#
#1320
1#
b00100111 &
#1330
0#
#1340
1#
b00101000 &
#1350
0#
#1360
1#
b00101001 &
#1370
0#
#1380
1#
b00101010 &
#1390
0#
#1400
1#
b00101011 &
#1410
0#
#1420
1#
b00101100 &
#1430
0#
#1440
1#
b00101101 &
#1450
0#
#1460
1#
b00101110 &
#1470
0#
#1480
1#
b00101111 &
#1490
0#
#1500
1#
b00110000 &
#1510
0#
#1520
1#
b00110001 &
#1530
0#
#1540
1#
b00110010 &
#1550
0#
#1560
1#
b00110011 &
#1570
0#
#1580
1#
b00110100 &
#1590
0#
#1600
1#
b00110101 &
#1610
0#
#1620
1#
b00110110 &
#1630
0#
#1640
1#
b00110111 &
#1650
0#
#1660
1#
b00111000 &
#1670
0#
#1680
1#
b00111001 &
#1690
0#
#1700
1#
b00111010 &
#1710
0#
#1720
1#
b00111011 &
#1730
0#
#1740
1#
b00111100 &
#1750
0#
#1760
1#
b00111101 &
#1770
0#
#1780
1#
b00111110 &
#1790
0#
#1800
1#
b00111111 &
#1810
0#
#1820
1#
b01000000 &
#1830
0#
#1840
1#
b01000001 &
#1850
0#
#1860
1#
b01000010 &
#1870
0#
#1880
1#
b01000011 &
#1890
0#
#1900
1#
b01000100 &
#1910
0#
#1920
1#
b01000101 &
#1930
0#
#1940
1#
b01000110 &
#1950
0#
#1960
1#
b01000111 &
#1970
0#
#1980
1#
b01001000 &
