task1/counter.sv
module counter #(
    parameter WIDTH = 8
)(
    // interface signals
    input logic clk,                   // clock
    input logic rst,                   // reset
    input logic en,                    // enable counter
    output logic [WIDTH-1:0] count     // count output
);

always_ff @(posedge clk)
    if (rst) count <= {WIDTH{1'b0}};
    else count <= count + {{WIDTH-1{1'b0}}, en};

endmodule

task2/counter.vcd
$version Generated by VerilatedVcd $end
$date Sat Oct 18 22:01:53 2025 $end
$timescale 1ps $end

 $scope module TOP $end
  $var wire  1 # clk $end
  $var wire  8 & count [7:0] $end
  $var wire  1 % en $end
  $var wire  1 $ rst $end
  $scope module counter $end
   $var wire 32 ' WIDTH [31:0] $end
   $var wire  1 # clk $end
   $var wire  8 & count [7:0] $end
   $var wire  1 % en $end
   $var wire  1 $ rst $end
  $upscope $end
 $upscope $end
$enddefinitions $end


#0
1#
1$
0%
b00000000 &
b00000000000000000000000000001000 '
#1
0#
#2
1#
1%
#3
0#
#4
1#
#5
0#
#6
1#
0$
#7
0#
#8
1#
b00000001 &
#9
0#
#10
1#
b00000010 &
#11
0#
#12
1#
b00000011 &
#13
0#
#14
1#
b00000100 &
#15
0#
#16
1#
b00000101 &
#17
0#
#18
1#
b00000110 &
#19
0#
#20
1#
b00000111 &
#21
0#
#22
1#
b00001000 &
#23
0#
#24
1#
b00001001 &
#25
0#
#26
1#
b00001010 &
#27
0#
#28
1#
b00001011 &
#29
0#
#30
1#
b00001100 &
#31
0#
#32
1#
1$
b00001101 &
#33
0#
#34
1#
0$
0%
b00000000 &
